email_api/__init__.py
email_api/emailapi.py
email_api-0.2.dist-info/LICENSE
email_api-0.2.dist-info/METADATA
email_api-0.2.dist-info/WHEEL
email_api-0.2.dist-info/top_level.txt
email_api-0.2.dist-info/RECORD
