Metadata-Version: 2.1
Name: email-api
Version: 0.2
Summary: quickly get the verification code from the temp email
Home-page: https://github.com/xu0329
Author: XuHongsheng
Author-email: xuhongsheng5@outlook.com
License: MIT
Keywords: email temp email verification code
Platform: any
Classifier: Programming Language :: Python :: 3
Classifier: License :: OSI Approved :: MIT License
Classifier: Operating System :: OS Independent
License-File: LICENSE
Requires-Dist: requests
